odoo/addons/website_snippet_openstreetmap/README.rst
odoo/addons/website_snippet_openstreetmap/__init__.py
odoo/addons/website_snippet_openstreetmap/__manifest__.py
odoo/addons/website_snippet_openstreetmap/demo/res_partner_demo.xml
odoo/addons/website_snippet_openstreetmap/description/icon.png
odoo/addons/website_snippet_openstreetmap/i18n/es.po
odoo/addons/website_snippet_openstreetmap/i18n/it.po
odoo/addons/website_snippet_openstreetmap/i18n/website_snippet_openstreetmap.pot
odoo/addons/website_snippet_openstreetmap/readme/CONTRIBUTORS.rst
odoo/addons/website_snippet_openstreetmap/readme/DESCRIPTION.rst
odoo/addons/website_snippet_openstreetmap/readme/USAGE.rst
odoo/addons/website_snippet_openstreetmap/static/description/icon.png
odoo/addons/website_snippet_openstreetmap/static/description/index.html
odoo/addons/website_snippet_openstreetmap/static/src/img/snippets_thumbs/s_openstreetmap.svg
odoo/addons/website_snippet_openstreetmap/static/src/js/utils.js
odoo/addons/website_snippet_openstreetmap/static/src/snippets/s_openstreetmap/000.js
odoo/addons/website_snippet_openstreetmap/static/src/snippets/s_openstreetmap/000.scss
odoo/addons/website_snippet_openstreetmap/static/src/snippets/s_openstreetmap/options.js
odoo/addons/website_snippet_openstreetmap/views/snippets/s_openstreetmap.xml
odoo/addons/website_snippet_openstreetmap/views/snippets/snippets.xml
odoo_addon_website_snippet_openstreetmap-15.0.1.0.0.11.dist-info/METADATA
odoo_addon_website_snippet_openstreetmap-15.0.1.0.0.11.dist-info/WHEEL
odoo_addon_website_snippet_openstreetmap-15.0.1.0.0.11.dist-info/top_level.txt
odoo_addon_website_snippet_openstreetmap-15.0.1.0.0.11.dist-info/RECORD
